minetext/VERSION
minetext/__init__.py
minetext/config.py
minetext/exceptions.py
minetext/mine.py
minetext/domain/__init__.py
minetext/domain/es_request.py
minetext/domain/user_auth.py
minetext/model/__init__.py
minetext/model/access_token.py
minetext/model/device_token.py
tests/__init__.py
tests/conftest.py
tests/test_mine.py
tests/test_user_auth.py
minetext-0.6.0.dist-info/LICENSE
minetext-0.6.0.dist-info/METADATA
minetext-0.6.0.dist-info/WHEEL
minetext-0.6.0.dist-info/top_level.txt
minetext-0.6.0.dist-info/RECORD
