Metadata-Version: 2.1
Name: minetext
Version: 0.6.0
Summary: Python client for MINE system
Home-page: https://gitlab-ce.gwdg.de/mine/mine-python
Author: Triet Doan
Author-email: triet.doan@gwdg.de
License: UNKNOWN
Platform: UNKNOWN
Classifier: Programming Language :: Python :: 3
Classifier: License :: OSI Approved :: MIT License
Classifier: Operating System :: OS Independent
Classifier: Intended Audience :: Science/Research
Classifier: Natural Language :: English
Classifier: Development Status :: 4 - Beta
Requires-Python: >=3.7
